pypi_helper/__init__.py
pypi_helper/__main__.py
pypi_helper-1.0.1.dist-info/LICENSE
pypi_helper-1.0.1.dist-info/METADATA
pypi_helper-1.0.1.dist-info/WHEEL
pypi_helper-1.0.1.dist-info/top_level.txt
pypi_helper-1.0.1.dist-info/RECORD
